README.md
setup.py
tungsten_prometheus_exporter/__init__.py
tungsten_prometheus_exporter/config.py
tungsten_prometheus_exporter/main.py
tungsten_prometheus_exporter/metric.py
tungsten_prometheus_exporter/scrape.py
tungsten_prometheus_exporter/utils.py
tungsten_prometheus_exporter.egg-info/PKG-INFO
tungsten_prometheus_exporter.egg-info/SOURCES.txt
tungsten_prometheus_exporter.egg-info/dependency_links.txt
tungsten_prometheus_exporter.egg-info/entry_points.txt
tungsten_prometheus_exporter.egg-info/requires.txt
tungsten_prometheus_exporter.egg-info/top_level.txt